{
  "/404": "pages/404.html",
  "/Floating": "pages/Floating.html",
  "/Hi": "pages/Hi.html",
  "/Locomotive": "pages/Locomotive.html",
  "/Newer": "pages/Newer.html",
  "/SunIcon": "pages/SunIcon.html",
  "/_app": "pages/_app.js",
  "/blog": "pages/blog.html",
  "/contact-us": "pages/contact-us.html",
  "/contact": "pages/contact.html",
  "/dream": "pages/dream.html",
  "/hover-effect.umd": "pages/hover-effect.umd.html",
  "/index copy": "pages/index copy.html",
  "/": "pages/index.html",
  "/ladee": "pages/ladee.html",
  "/lady": "pages/lady.html",
  "/locoFinally": "pages/locoFinally.html",
  "/locoLerp": "pages/locoLerp.html",
  "/locos": "pages/locos.html",
  "/media-center": "pages/media-center.html",
  "/new": "pages/new.html",
  "/old-blog": "pages/old-blog.html",
  "/partner-with-us-prev-prev": "pages/partner-with-us-prev-prev.html",
  "/partner-with-us-prev": "pages/partner-with-us-prev.html",
  "/partner-with-us": "pages/partner-with-us.html",
  "/problems-we-solve": "pages/problems-we-solve.html",
  "/products-we-offer": "pages/products-we-offer.html",
  "/shrink": "pages/shrink.html",
  "/skew": "pages/skew.html",
  "/zoomOutScroll": "pages/zoomOutScroll.html",
  "/_error": "pages/_error.js",
  "/_document": "pages/_document.js"
}